django_tilestache/__init__.py
django_tilestache/apps.py
django_tilestache/base.py
django_tilestache/caches.py
django_tilestache/choices.py
django_tilestache/compilers.py
django_tilestache/configuration.py
django_tilestache/exceptions.py
django_tilestache/models.py
django_tilestache/polymorfic.py
django_tilestache/serializers.py
django_tilestache/server.py
django_tilestache/settings.py
django_tilestache/signals.py
django_tilestache/urls.py
django_tilestache/utils.py
django_tilestache/views.py
django_tilestache/viewsets.py
django_tilestache/migrations/0001_initial.py
django_tilestache/migrations/__init__.py
django_tilestache/static/css/django_tilestache.css
django_tilestache/static/js/django_tilestache.js
django_tilestache/templates/django_tilestache/base.html
django_tilestache-2.0.9.dist-info/AUTHORS.rst
django_tilestache-2.0.9.dist-info/LICENSE
django_tilestache-2.0.9.dist-info/METADATA
django_tilestache-2.0.9.dist-info/WHEEL
django_tilestache-2.0.9.dist-info/top_level.txt
django_tilestache-2.0.9.dist-info/RECORD
