Metadata-Version: 2.1
Name: django-tilestache
Version: 2.0.9
Summary: Command and Control Center for Tilestache, inside a django app
Home-page: https://gitlab.com/geoadmin-opensource/django-tilestache
Author: George Silva
Author-email: georger.silva@gmail.com
License: MIT
Keywords: django-tilestache
Platform: UNKNOWN
Classifier: Development Status :: 3 - Alpha
Classifier: Framework :: Django
Classifier: Framework :: Django :: 1.8
Classifier: Framework :: Django :: 1.9
Classifier: Framework :: Django :: 1.10
Classifier: Framework :: Django :: 1.11
Classifier: Intended Audience :: Developers
Classifier: License :: OSI Approved :: BSD License
Classifier: Natural Language :: English
Classifier: Programming Language :: Python :: 2
Classifier: Programming Language :: Python :: 2.7
Classifier: Programming Language :: Python :: 3
Classifier: Programming Language :: Python :: 3.3
Classifier: Programming Language :: Python :: 3.4
Classifier: Programming Language :: Python :: 3.5
Requires-Dist: pytz
Requires-Dist: django
Requires-Dist: django-appconf
Requires-Dist: tilestache
Requires-Dist: jsonfield
Requires-Dist: apscheduler
Requires-Dist: djangorestframework
Requires-Dist: djangorestframework-gis
Requires-Dist: djangorestframework-filters
Requires-Dist: requests
Requires-Dist: pylru
Requires-Dist: six
